virginia_clemm_poe/__init__.py
virginia_clemm_poe/__main__.py
virginia_clemm_poe/_version.py
virginia_clemm_poe/api.py
virginia_clemm_poe/balance_scraper.py
virginia_clemm_poe/bots.py
virginia_clemm_poe/browser_manager.py
virginia_clemm_poe/browser_pool.py
virginia_clemm_poe/config.py
virginia_clemm_poe/exceptions.py
virginia_clemm_poe/poe_session.py
virginia_clemm_poe/type_guards.py
virginia_clemm_poe/types.py
virginia_clemm_poe/updater.py
virginia_clemm_poe/utils.py
virginia_clemm_poe/data/poe_bots.json
virginia_clemm_poe/utils/__init__.py
virginia_clemm_poe/utils/cache.py
virginia_clemm_poe/utils/crash_recovery.py
virginia_clemm_poe/utils/logger.py
virginia_clemm_poe/utils/memory.py
virginia_clemm_poe/utils/paths.py
virginia_clemm_poe/utils/timeout.py
virginia_clemm_poe/utils/validation.py
virginia_clemm_poe-1.0.33.dist-info/METADATA
virginia_clemm_poe-1.0.33.dist-info/WHEEL
virginia_clemm_poe-1.0.33.dist-info/entry_points.txt
virginia_clemm_poe-1.0.33.dist-info/licenses/LICENSE
virginia_clemm_poe-1.0.33.dist-info/RECORD
