Metadata-Version: 2.4
Name: virginia-clemm-poe
Version: 1.0.33
Summary: A Python package providing programmatic access to Poe.com model data with pricing information
Project-URL: Homepage, https://github.com/twardoch/virginia-clemm-poe
Project-URL: Repository, https://github.com/twardoch/virginia-clemm-poe
Project-URL: Issues, https://github.com/twardoch/virginia-clemm-poe/issues
Author-email: Adam Twardoch <adam+github@twardoch.com>
License: Apache-2.0
License-File: LICENSE
Classifier: Development Status :: 4 - Beta
Classifier: License :: OSI Approved :: Apache Software License
Classifier: Operating System :: OS Independent
Classifier: Programming Language :: Python :: 3
Classifier: Programming Language :: Python :: 3.12
Requires-Python: >=3.12
Requires-Dist: aiohttp>=3.9.0
Requires-Dist: beautifulsoup4>=4.12.0
Requires-Dist: fire>=0.5.0
Requires-Dist: httpx>=0.24.0
Requires-Dist: loguru>=0.7.0
Requires-Dist: mkdocs-material>=9.6.16
Requires-Dist: mkdocstrings[python]>=0.30.0
Requires-Dist: playwrightauthor>=1.0.6
Requires-Dist: psutil>=5.9.0
Requires-Dist: pydantic>=2.5.0
Requires-Dist: rich>=13.0.0
